indexify_dspy/__init__.py
indexify_dspy/retriever.py
indexify_dspy/tests.py
indexify_dspy-0.0.1.dist-info/METADATA
indexify_dspy-0.0.1.dist-info/WHEEL
indexify_dspy-0.0.1.dist-info/RECORD
